pycastiphone_client/__init__.py
pycastiphone_client/client.py
pycastiphone_client/exceptions.py
pycastiphone_client/helpers.py
pycastiphone_client/resources/__init__.py
pycastiphone_client/resources/cliente.py
pycastiphone_client/resources/login.py
tests/resources/__init__.py
tests/resources/test_cliente.py
tests/resources/test_login.py
tests/resources/cassettes/test_cliente/ClienteTests.test_create.yaml
tests/resources/cassettes/test_login/LoginTests.test_authenticate.yaml
pycastiphone_client-0.1.0.dist-info/METADATA
pycastiphone_client-0.1.0.dist-info/WHEEL
pycastiphone_client-0.1.0.dist-info/top_level.txt
pycastiphone_client-0.1.0.dist-info/RECORD
