Metadata-Version: 2.1
Name: pycastiphone-client
Version: 0.1.0
Summary: Python wrapper for Castiphone (using REST API)
Home-page: https://gitlab.com/coopdevs/pycastiphone-client
Author: Coopdevs
Author-email: info@coopdevs.org
Maintainer: Konykon
License: UNKNOWN
Platform: UNKNOWN
Classifier: Development Status :: 3 - Alpha
Classifier: Operating System :: POSIX :: Linux
Classifier: Programming Language :: Python :: 3.8
Requires-Dist: requests
